{"mc":{"monster30068_0a":{"frameRate":10,"events":[],"frames":[{"res":"DF0025BE","x":-23,"y":-28},{"res":"FB918325","x":-23,"y":-23},{"res":"105FB5B7","x":-23,"y":-43},{"res":"38D39D98","x":-23,"y":-43},{"res":"CAB9B49F","x":-23,"y":-41},{"res":"EF1C785E","x":-23,"y":-37}]}},"res":{"EF1C785E":{"x":0,"y":60,"w":44,"h":53},"38D39D98":{"x":44,"y":0,"w":44,"h":59},"105FB5B7":{"x":0,"y":0,"w":44,"h":60},"CAB9B49F":{"x":44,"y":59,"w":44,"h":57},"FB918325":{"x":44,"y":116,"w":44,"h":39},"DF0025BE":{"x":0,"y":113,"w":44,"h":44}}}