{
  "mc": {
    "monster30212_0s": {
      "frameRate": 6,
      "frames": [
        {
          "res": "101",
          "x": -25,
          "y": -84
        },
        {
          "res": "102",
          "x": -26,
          "y": -83
        },
        {
          "res": "103",
          "x": -26,
          "y": -84
        }
      ]
    }
  },
  "res": {
    "101": {
      "x": 0,
      "y": 0,
      "w": 49,
      "h": 108
    },
    "102": {
      "x": 49,
      "y": 0,
      "w": 50,
      "h": 108
    },
    "103": {
      "x": 99,
      "y": 0,
      "w": 50,
      "h": 110
    }
  }
}