{"mc":{"monster30049_4w":{"frameRate":10,"events":[],"frames":[{"res":"FE5A8F3C","x":-43,"y":-64},{"res":"BD2D3535","x":-45,"y":-61},{"res":"F233BB3C","x":-46,"y":-61},{"res":"706CF1C4","x":-55,"y":-56},{"res":"BD2670E1","x":-58,"y":-55},{"res":"578011FA","x":-48,"y":-62}]}},"res":{"578011FA":{"x":0,"y":0,"w":88,"h":79},"706CF1C4":{"x":278,"y":0,"w":100,"h":64},"FE5A8F3C":{"x":378,"y":63,"w":84,"h":72},"F233BB3C":{"x":88,"y":0,"w":95,"h":69},"BD2670E1":{"x":378,"y":0,"w":101,"h":63},"BD2D3535":{"x":183,"y":0,"w":95,"h":69}}}