{
  "mc": {
    "monster30171_3d": {
      "frameRate": 6,
      "frames": [
        {
          "res": "Dead_1_0000",
          "x": -125,
          "y": -236
        },
        {
          "res": "Dead_1_0001",
          "x": -127,
          "y": -250
        },
        {
          "res": "Dead_1_0002",
          "x": -125,
          "y": -241
        },
        {
          "res": "Dead_1_0003",
          "x": -87,
          "y": -164
        },
        {
          "res": "Dead_1_0004",
          "x": -92,
          "y": -132
        },
        {
          "res": "Dead_1_0005",
          "x": -107,
          "y": -88
        }
      ]
    }
  },
  "res": {
    "Dead_1_0000": {
      "x": 0,
      "y": 0,
      "w": 231,
      "h": 285
    },
    "Dead_1_0001": {
      "x": 231,
      "y": 0,
      "w": 198,
      "h": 280
    },
    "Dead_1_0002": {
      "x": 429,
      "y": 0,
      "w": 208,
      "h": 271
    },
    "Dead_1_0003": {
      "x": 637,
      "y": 0,
      "w": 213,
      "h": 198
    },
    "Dead_1_0004": {
      "x": 850,
      "y": 0,
      "w": 250,
      "h": 181
    },
    "Dead_1_0005": {
      "x": 1100,
      "y": 0,
      "w": 281,
      "h": 179
    }
  }
}