{
  "mc": {
    "monster30217_1s": {
      "frameRate": 5,
      "frames": [
        {
          "res": "Stand_3_0000",
          "x": -63,
          "y": -154
        },
        {
          "res": "Stand_3_0001",
          "x": -66,
          "y": -154
        },
        {
          "res": "Stand_3_0002",
          "x": -63,
          "y": -159
        },
        {
          "res": "Stand_3_0003",
          "x": -59,
          "y": -158
        }
      ]
    }
  },
  "res": {
    "Stand_3_0000": {
      "x": 0,
      "y": 0,
      "w": 182,
      "h": 178
    },
    "Stand_3_0001": {
      "x": 182,
      "y": 0,
      "w": 183,
      "h": 177
    },
    "Stand_3_0002": {
      "x": 365,
      "y": 0,
      "w": 172,
      "h": 183
    },
    "Stand_3_0003": {
      "x": 537,
      "y": 0,
      "w": 171,
      "h": 183
    }
  }
}