{"mc":{"monster30094_0w":{"frameRate":10,"events":[],"frames":[{"res":"77575F64","x":-32,"y":-88},{"res":"3E2B9DBD","x":-32,"y":-87},{"res":"D8C847E2","x":-31,"y":-87},{"res":"EBC406EE","x":-30,"y":-87},{"res":"8F98B7A6","x":-30,"y":-96},{"res":"6F3CC267","x":-32,"y":-97}]}},"res":{"8F98B7A6":{"x":138,"y":97,"w":65,"h":114},"D8C847E2":{"x":0,"y":118,"w":73,"h":97},"6F3CC267":{"x":0,"y":0,"w":66,"h":118},"3E2B9DBD":{"x":138,"y":0,"w":77,"h":97},"EBC406EE":{"x":73,"y":211,"w":66,"h":102},"77575F64":{"x":66,"y":0,"w":72,"h":105}}}