{
  "mc": {
    "monster30212_1a": {
      "frameRate": 15,
      "frames": [
        {
          "res": "128",
          "x": -56,
          "y": -80
        },
        {
          "res": "129",
          "x": -74,
          "y": -76
        },
        {
          "res": "130",
          "x": -54,
          "y": -93
        },
        {
          "res": "131",
          "x": -54,
          "y": -92
        },
        {
          "res": "132",
          "x": -50,
          "y": -82
        },
        {
          "res": "133",
          "x": -48,
          "y": -80
        }
      ]
    }
  },
  "res": {
    "128": {
      "x": 0,
      "y": 0,
      "w": 99,
      "h": 99
    },
    "129": {
      "x": 99,
      "y": 0,
      "w": 115,
      "h": 92
    },
    "130": {
      "x": 214,
      "y": 0,
      "w": 129,
      "h": 108
    },
    "131": {
      "x": 343,
      "y": 0,
      "w": 124,
      "h": 107
    },
    "132": {
      "x": 467,
      "y": 0,
      "w": 108,
      "h": 112
    },
    "133": {
      "x": 575,
      "y": 0,
      "w": 97,
      "h": 114
    }
  }
}