{"mc":{
	"monster30182_3a":{
		"frameRate":10,
		"events":[
			
			],
		"frames":[
			
			{
			"res":"FFF36218",
			"x":-58,
			"y":-152
			},
			{
			"res":"E6107DBB",
			"x":-106,
			"y":-221
			},
			{
			"res":"552B1AC4",
			"x":-256,
			"y":-285
			},
			{
			"res":"AF7284CE",
			"x":-280,
			"y":-273
			},
			{
			"res":"65C81A8E",
			"x":-256,
			"y":-305
			},
			{
			"res":"C7F9F30C",
			"x":-47,
			"y":-143
			},
			{
			"res":"85F4FCE6",
			"x":-50,
			"y":-146
			},
			{
			"res":"4A885257",
			"x":-55,
			"y":-157
			}
			]
}},
	"res":{
		"4A885257":{"x":676,"y":585,"w":285,"h":267},
		"552B1AC4":{"x":347,"y":285,"w":327,"h":294},
		"C7F9F30C":{"x":1,"y":317,"w":298,"h":275},
		"FFF36218":{"x":301,"y":581,"w":267,"h":228},
		"AF7284CE":{"x":347,"y":1,"w":351,"h":282},
		"85F4FCE6":{"x":700,"y":1,"w":301,"h":286},
		"E6107DBB":{"x":676,"y":289,"w":259,"h":294},
		"65C81A8E":{"x":1,"y":1,"w":344,"h":314}
	}}