{"mc":{"monster30069_0a":{"frameRate":10,"events":[],"frames":[{"res":"F49436C5","x":-61,"y":-83},{"res":"223310C4","x":-53,"y":-89},{"res":"6C3EA8DC","x":-56,"y":-93},{"res":"A0E1E3C8","x":-56,"y":-90},{"res":"C5E75D3D","x":-57,"y":-85},{"res":"5D32B724","x":-55,"y":-86}]}},"res":{"223310C4":{"x":350,"y":0,"w":104,"h":98},"C5E75D3D":{"x":0,"y":0,"w":125,"h":95},"F49436C5":{"x":0,"y":95,"w":109,"h":92},"6C3EA8DC":{"x":242,"y":96,"w":98,"h":102},"5D32B724":{"x":242,"y":0,"w":108,"h":96},"A0E1E3C8":{"x":125,"y":0,"w":117,"h":100}}}