{
  "mc": {
    "monster30201_3s": {
      "frameRate": 6,
      "frames": [
        {
          "res": "155",
          "x": -114,
          "y": -195
        },
        {
          "res": "156",
          "x": -115,
          "y": -194
        },
        {
          "res": "157",
          "x": -114,
          "y": -194
        }
      ]
    }
  },
  "res": {
    "155": {
      "x": 0,
      "y": 0,
      "w": 263,
      "h": 264
    },
    "156": {
      "x": 263,
      "y": 0,
      "w": 262,
      "h": 262
    },
    "157": {
      "x": 525,
      "y": 0,
      "w": 260,
      "h": 262
    }
  }
}