{"mc":{"monster30026_4a":{"frameRate":10,"events":[],"frames":[{"res":"FF86F066","x":-69,"y":-71},{"res":"4BE86F2A","x":-41,"y":-114},{"res":"8EE5CFFE","x":-50,"y":-120},{"res":"406B59C8","x":-37,"y":-71},{"res":"5C7F5849","x":-26,"y":-44},{"res":"AB9E0A21","x":-34,"y":-50}]}},"res":{"5C7F5849":{"x":134,"y":127,"w":54,"h":78},"AB9E0A21":{"x":65,"y":88,"w":69,"h":77},"406B59C8":{"x":0,"y":120,"w":54,"h":83},"FF86F066":{"x":65,"y":0,"w":86,"h":88},"4BE86F2A":{"x":151,"y":0,"w":58,"h":127},"8EE5CFFE":{"x":0,"y":0,"w":65,"h":120}}}