{"mc":{"monster30026_1a":{"frameRate":10,"events":[],"frames":[{"res":"1E6B3570","x":-12,"y":-66},{"res":"537E8842","x":-36,"y":-55},{"res":"8D8140E9","x":-44,"y":-59},{"res":"6889C6A","x":-12,"y":-92},{"res":"2F89EFB","x":-35,"y":-66},{"res":"641D893C","x":-29,"y":-73}]}},"res":{"8D8140E9":{"x":153,"y":80,"w":83,"h":75},"2F89EFB":{"x":153,"y":0,"w":83,"h":80},"537E8842":{"x":67,"y":107,"w":75,"h":70},"6889C6A":{"x":86,"y":0,"w":67,"h":107},"641D893C":{"x":0,"y":0,"w":86,"h":88},"1E6B3570":{"x":0,"y":88,"w":67,"h":81}}}