{"mc":{"monster30076_3w":{"frameRate":10,"events":[],"frames":[{"res":"3974700D","x":-40,"y":-47},{"res":"3508EDD0","x":-35,"y":-47},{"res":"18F1AA1B","x":-34,"y":-48},{"res":"57AC4FF9","x":-34,"y":-49},{"res":"1FEA5B27","x":-36,"y":-47},{"res":"75D90F47","x":-39,"y":-47}]}},"res":{"3508EDD0":{"x":166,"y":69,"w":83,"h":62},"1FEA5B27":{"x":85,"y":65,"w":81,"h":65},"75D90F47":{"x":0,"y":0,"w":85,"h":69},"57AC4FF9":{"x":168,"y":0,"w":77,"h":69},"3974700D":{"x":85,"y":0,"w":83,"h":65},"18F1AA1B":{"x":0,"y":69,"w":80,"h":65}}}