{
  "mc": {
    "monster30195_2d": {
      "frameRate": 15,
      "frames": [
        {
          "res": "Dead_2_0000",
          "x": -72,
          "y": -248
        },
        {
          "res": "Dead_2_0001",
          "x": -115,
          "y": -209
        },
        {
          "res": "Dead_2_0002",
          "x": -154,
          "y": -226
        },
        {
          "res": "Dead_2_0003",
          "x": -71,
          "y": -186
        },
        {
          "res": "Dead_2_0004",
          "x": -38,
          "y": -99
        },
        {
          "res": "Dead_2_0005",
          "x": -39,
          "y": -84
        }
      ]
    }
  },
  "res": {
    "Dead_2_0000": {
      "x": 0,
      "y": 0,
      "w": 191,
      "h": 287
    },
    "Dead_2_0001": {
      "x": 191,
      "y": 0,
      "w": 272,
      "h": 248
    },
    "Dead_2_0002": {
      "x": 463,
      "y": 0,
      "w": 224,
      "h": 290
    },
    "Dead_2_0003": {
      "x": 687,
      "y": 0,
      "w": 247,
      "h": 233
    },
    "Dead_2_0004": {
      "x": 934,
      "y": 0,
      "w": 290,
      "h": 186
    },
    "Dead_2_0005": {
      "x": 1224,
      "y": 0,
      "w": 290,
      "h": 175
    }
  }
}