{"mc":{
	"body805_0_0a":{
		"frameRate":8,
		"events":[
			
			],
		"frames":[
			
			{
			"res":"FAD1D669",
			"x":-31,
			"y":-92
			},
			{
			"res":"71CC7E49",
			"x":-95,
			"y":-86
			},
			{
			"res":"D1D6B581",
			"x":-39,
			"y":-92
			},
			{
			"res":"C8C33546",
			"x":-39,
			"y":-104
			},
			{
			"res":"D49F9CEE",
			"x":-39,
			"y":-114
			},
			{
			"res":"AB8766F7",
			"x":-39,
			"y":-119
			}
			]
}},
	"res":{
		"C8C33546":{"x":1,"y":156,"w":129,"h":137},
		"AB8766F7":{"x":1,"y":1,"w":140,"h":153},
		"D1D6B581":{"x":132,"y":156,"w":114,"h":125},
		"D49F9CEE":{"x":143,"y":1,"w":100,"h":147},
		"71CC7E49":{"x":1,"y":295,"w":141,"h":124},
		"FAD1D669":{"x":245,"y":1,"w":86,"h":131}
	}}