{"mc":{
	"body803_1_7r":{
		"frameRate":8,
		"events":[
			
			],
		"frames":[
			
			{
			"res":"B7EDEA2D",
			"x":-52,
			"y":-74
			},
			{
			"res":"D4E5A779",
			"x":-64,
			"y":-111
			},
			{
			"res":"629D97C",
			"x":-64,
			"y":-136
			},
			{
			"res":"4FDF8FD2",
			"x":-49,
			"y":-148
			},
			{
			"res":"E0A82911",
			"x":-59,
			"y":-124
			},
			{
			"res":"8EE4E22",
			"x":-60,
			"y":-93
			}
			]
}},
	"res":{
		"4FDF8FD2":{"x":118,"y":1,"w":99,"h":158},
		"B7EDEA2D":{"x":119,"y":281,"w":107,"h":86},
		"D4E5A779":{"x":112,"y":161,"w":115,"h":118},
		"8EE4E22":{"x":1,"y":281,"w":116,"h":101},
		"629D97C":{"x":1,"y":1,"w":115,"h":141},
		"E0A82911":{"x":1,"y":144,"w":109,"h":133}
	}}