{"mc":{
	"chenghao209":{
		"frameRate":12,
		"events":[
			
			],
		"frames":[
			
			{
			"res":"AFA79029",
			"x":-123,
			"y":-114
			},
			{
			"res":"1D1E498",
			"x":-129,
			"y":-132
			},
			{
			"res":"D52367D6",
			"x":-136,
			"y":-132
			},
			{
			"res":"51FD2FCB",
			"x":-143,
			"y":-127
			},
			{
			"res":"AC9051FF",
			"x":-151,
			"y":-115
			},
			{
			"res":"F991C8AA",
			"x":-160,
			"y":-139
			},
			{
			"res":"26206F3F",
			"x":-165,
			"y":-144
			},
			{
			"res":"A162AA8F",
			"x":-161,
			"y":-155
			},
			{
			"res":"1F4C3C3C",
			"x":-151,
			"y":-149
			},
			{
			"res":"6F0B26EC",
			"x":-142,
			"y":-146
			},
			{
			"res":"389198F1",
			"x":-135,
			"y":-136
			},
			{
			"res":"C16FF288",
			"x":-129,
			"y":-117
			}
			]
}},
	"res":{
		"A162AA8F":{"x":1,"y":1,"w":330,"h":392},
		"AFA79029":{"x":297,"y":1513,"w":254,"h":350},
		"F991C8AA":{"x":333,"y":1,"w":329,"h":374},
		"D52367D6":{"x":337,"y":377,"w":280,"h":384},
		"26206F3F":{"x":1,"y":395,"w":334,"h":380},
		"AC9051FF":{"x":297,"y":1163,"w":310,"h":348},
		"51FD2FCB":{"x":337,"y":763,"w":294,"h":364},
		"1F4C3C3C":{"x":1,"y":777,"w":311,"h":384},
		"C16FF288":{"x":664,"y":1,"w":266,"h":353},
		"1D1E498":{"x":619,"y":377,"w":267,"h":370},
		"389198F1":{"x":633,"y":763,"w":278,"h":372},
		"6F0B26EC":{"x":1,"y":1163,"w":294,"h":383}
	}}