{"mc":{
	"chenghao280":{
		"frameRate":12,
		"events":[
			
			],
		"frames":[
			
			{
			"res":"EBE0AEAF",
			"x":-123,
			"y":-94
			},
			{
			"res":"BA7C39D0",
			"x":-127,
			"y":-96
			},
			{
			"res":"B4681FD2",
			"x":-129,
			"y":-96
			},
			{
			"res":"59A77240",
			"x":-132,
			"y":-97
			},
			{
			"res":"12B12C42",
			"x":-133,
			"y":-98
			},
			{
			"res":"D5584BF6",
			"x":-136,
			"y":-98
			},
			{
			"res":"FB1BB1BD",
			"x":-137,
			"y":-99
			},
			{
			"res":"8B5D79B9",
			"x":-136,
			"y":-98
			},
			{
			"res":"1C8974CC",
			"x":-133,
			"y":-98
			},
			{
			"res":"7ED52355",
			"x":-132,
			"y":-97
			},
			{
			"res":"568DF49C",
			"x":-129,
			"y":-96
			},
			{
			"res":"90824A97",
			"x":-127,
			"y":-96
			}
			]
}},
	"res":{
		"8B5D79B9":{"x":560,"y":1,"w":276,"h":126},
		"90824A97":{"x":264,"y":375,"w":256,"h":115},
		"7ED52355":{"x":1,"y":134,"w":267,"h":116},
		"B4681FD2":{"x":1,"y":252,"w":261,"h":115},
		"EBE0AEAF":{"x":522,"y":378,"w":249,"h":113},
		"D5584BF6":{"x":1,"y":1,"w":276,"h":131},
		"FB1BB1BD":{"x":279,"y":1,"w":279,"h":129},
		"1C8974CC":{"x":548,"y":256,"w":271,"h":120},
		"12B12C42":{"x":560,"y":129,"w":271,"h":125},
		"BA7C39D0":{"x":1,"y":369,"w":256,"h":115},
		"59A77240":{"x":279,"y":132,"w":267,"h":124},
		"568DF49C":{"x":264,"y":258,"w":261,"h":115}
	}}