{"mc":{"body016_0_3w":{"frameRate":8,"events":[],"frames":[{"res":"D4D1AFC4","x":-16,"y":-59},{"res":"3DD82FC9","x":-14,"y":-60},{"res":"A42992FE","x":-11,"y":-60},{"res":"D6D6C4B8","x":-19,"y":-59},{"res":"4593384B","x":-16,"y":-60},{"res":"3FBA9989","x":-13,"y":-60}]}},"res":{"D6D6C4B8":{"x":1,"y":1,"w":61,"h":72},"3FBA9989":{"x":58,"y":79,"w":54,"h":73},"D4D1AFC4":{"x":64,"y":1,"w":57,"h":76},"A42992FE":{"x":60,"y":154,"w":53,"h":70},"3DD82FC9":{"x":1,"y":75,"w":55,"h":73},"4593384B":{"x":1,"y":154,"w":57,"h":69}}}