{"mc":{"body004_0_1w":{"frameRate":8,"events":[],"frames":[{"res":"194A8742","x":-19,"y":-62},{"res":"69456C04","x":-16,"y":-62},{"res":"AFC4F83D","x":-15,"y":-62},{"res":"83DDD42C","x":-18,"y":-62},{"res":"F175949","x":-16,"y":-61},{"res":"1B9F2D2F","x":-15,"y":-62}]}},"res":{"69456C04":{"x":60,"y":149,"w":57,"h":70},"AFC4F83D":{"x":63,"y":75,"w":57,"h":72},"194A8742":{"x":63,"y":1,"w":61,"h":72},"83DDD42C":{"x":1,"y":1,"w":60,"h":77},"F175949":{"x":1,"y":80,"w":57,"h":72},"1B9F2D2F":{"x":1,"y":154,"w":57,"h":69}}}