{"mc":{"body002_1_1a":{"frameRate":8,"events":[],"frames":[{"res":"76C6FE95","x":-9,"y":-56},{"res":"E44595A0","x":-27,"y":-49},{"res":"812B1ADB","x":-11,"y":-62},{"res":"EBCE0D34","x":-15,"y":-62},{"res":"121447E6","x":-17,"y":-60},{"res":"B00CA2FB","x":-13,"y":-61}]}},"res":{"812B1ADB":{"x":98,"y":74,"w":55,"h":75},"B00CA2FB":{"x":169,"y":68,"w":62,"h":73},"E44595A0":{"x":169,"y":1,"w":70,"h":65},"121447E6":{"x":98,"y":1,"w":69,"h":71},"EBCE0D34":{"x":1,"y":1,"w":95,"h":74},"76C6FE95":{"x":1,"y":77,"w":55,"h":71}}}